wechat/__init__.py
wechat/__init__.pyc
wechat/__version__.py
wechat/__version__.pyc
wechat/api.py
wechat/api.pyc
wechat/auth.py
wechat/auth.pyc
wechat/compat.py
wechat/compat.pyc
wechat/exceptions.py
wechat/exceptions.pyc
wechat/mpapi.py
wechat/mpapi.pyc
wechat/pay.py
wechat/pay.pyc
wechat/result.py
wechat/result.pyc
wechat/settings.py
wechat/settings.pyc
wechat/sign.py
wechat/sign.pyc
wechat/utils.py
wechat/utils.pyc
wechat/__pycache__/__init__.cpython-36.pyc
wechat/__pycache__/__version__.cpython-36.pyc
wechat/__pycache__/api.cpython-36.pyc
wechat/__pycache__/auth.cpython-36.pyc
wechat/__pycache__/compat.cpython-36.pyc
wechat/__pycache__/exceptions.cpython-36.pyc
wechat/__pycache__/mpapi.cpython-36.pyc
wechat/__pycache__/pay.cpython-36.pyc
wechat/__pycache__/result.cpython-36.pyc
wechat/__pycache__/settings.cpython-36.pyc
wechat/__pycache__/sign.cpython-36.pyc
wechat/__pycache__/utils.cpython-36.pyc
wechat_requests-1.0.0.dist-info/DESCRIPTION.rst
wechat_requests-1.0.0.dist-info/METADATA
wechat_requests-1.0.0.dist-info/RECORD
wechat_requests-1.0.0.dist-info/WHEEL
wechat_requests-1.0.0.dist-info/metadata.json
wechat_requests-1.0.0.dist-info/top_level.txt
